acronymmaker
