Metadata-Version: 2.1
Name: acronymmaker
Version: 0.1.1
Summary: Create awesome acronyms for your projects!
Home-page: https://gitlab.com/acronym-maker/python-implementation
Author: Romain Wallon
Author-email: romain.gael.wallon@gmail.com
License: GNU General Public License, Version 3
Keywords: acronym acronyms build create make word words
Platform: UNKNOWN
Classifier: Programming Language :: Python :: 3
Classifier: License :: OSI Approved :: GNU General Public License v3 (GPLv3)
Classifier: Development Status :: 4 - Beta
Classifier: Environment :: Console
Classifier: Operating System :: OS Independent
